[
  {
    "title": "Elden-Rim Together",
    "description": "ACT RPG Modpack that features modern combat and gameplay features thats not only made for single player but was made for online coop in mind",
    "author": "DJLegends",
    "maintainers": [
      "github/DJLegends1011"
    ],
    "game": "skyrimspecialedition",
    "official": false,
    "tags": [
      "Overhaul",
      "BFCO",
      "Roleplay",
      "Balance",
      "STR",
      "Visuals",
      "Vokriinator Black"
    ],
    "nsfw": false,
    "utility_list": false,
    "image_contains_title": true,
    "DisplayVersionOnlyInInstallerView": false,
    "force_down": false,
    "links": {
      "image": "https://raw.githubusercontent.com/DJLegends1011/Elden-Rim-Together/main/modlist-image.png",
      "readme": "https://github.com/DJLegends1011/Elden-Rim/blob/main/README.md",
      "download": "https://authored-files.wabbajack.org/EldenRim Together.wabbajack_7d93003f-067f-4859-987d-4481d5a74809",
      "machineURL": "EldenRim",
      "discordURL": "https://discord.gg/YwU4dF2X9V",
      "websiteURL": ""
    },
    "download_metadata": {
      "Hash": "EuybuQW2hAs=",
      "Size": 78861867,
      "NumberOfArchives": 673,
      "SizeOfArchives": 54582869703,
      "NumberOfInstalledFiles": 103750,
      "SizeOfInstalledFiles": 85710662442,
      "TotalSize": 140293532145
    },
    "version": "3.2.8",
    "dateCreated": "1970-01-01T00:00:00Z",
    "dateUpdated": "2025-10-09T20:05:27.7545588Z",
    "repositoryName": ""
  }
]