[
  {
    "title": "Elden-Rim Together",
    "description": "ACT RPG Modpack that features modern combat and gameplay features thats not only made for single player but was made for online coop in mind",
    "author": "DJLegends",
    "maintainers": [
      "github/DJLegends1011"
    ],
    "game": "skyrimspecialedition",
    "official": false,
    "tags": [
      "Overhaul",
      "BFCO",
      "Roleplay",
      "Balance",
      "STR",
      "Visuals",
      "Vokriinator Black"
    ],
    "nsfw": false,
    "utility_list": false,
    "image_contains_title": true,
    "DisplayVersionOnlyInInstallerView": false,
    "force_down": false,
    "links": {
      "image": "https://raw.githubusercontent.com/DJLegends1011/Elden-Rim-Together/main/modlist-image.png",
      "readme": "https://github.com/DJLegends1011/Elden-Rim/blob/main/README.md",
      "download": "https://authored-files.wabbajack.org/EldenRim Together.wabbajack_4e67971a-6c89-4dc0-b38a-3ca6416e6ba4",
      "machineURL": "EldenRim",
      "discordURL": "https://discord.gg/YwU4dF2X9V",
      "websiteURL": "",
      "nexusCollection": {
        "collectionId": "458979",
        "slug": "h2erl1",
        "domainName": "skyrimspecialedition",
        "lastRevisionNumber": 4
      }
    },
    "download_metadata": {
      "Hash": "WaSbbI/Pq4w=",
      "Size": 89155501,
      "NumberOfArchives": 703,
      "SizeOfArchives": 55554321617,
      "NumberOfInstalledFiles": 106414,
      "SizeOfInstalledFiles": 82215359263,
      "TotalSize": 137769680880
    },
    "version": "3.4.2",
    "dateCreated": "1970-01-01T00:00:00Z",
    "dateUpdated": "2026-06-12T23:25:47.2587142Z",
    "repositoryName": ""
  }
]